PyOdataEdmModel/EdmModel.py
PyOdataEdmModel/__init__.py
PyOdataEdmModel/create_model.py
PyOdataEdmModel/odata_mapper.py
PyOdataEdmModel/primitives.py
PyOdataEdmModel/config/settings.json
PyOdataEdmModel/config/template.json
PyOdataEdmModel-1.0.5.data/data/config/settings.json
PyOdataEdmModel-1.0.5.data/data/config/template.json
unittests/__init__.py
unittests/test_EdmModel.py
unittests/test_create_model.py
unittests/test_odata_mapper.py
PyOdataEdmModel-1.0.5.dist-info/LICENSE
PyOdataEdmModel-1.0.5.dist-info/METADATA
PyOdataEdmModel-1.0.5.dist-info/WHEEL
PyOdataEdmModel-1.0.5.dist-info/top_level.txt
PyOdataEdmModel-1.0.5.dist-info/RECORD
