Metadata-Version: 2.1
Name: PyOdataEdmModel
Version: 1.0.5
Summary: The ODataEdmBuilder is a Python class that facilitates the construction of an Entity Data Model (EDM) for OData services.
Author: Wessel Reijngoud
Author-email: wreijngoud@ilionx.com
Project-URL: Source, https://github.com/wesselreijngoud/PyOdataEdmModel
Keywords: odata edmmodel metadata
License-File: LICENSE
Requires-Dist: pandas (==2.1.1)
